oshconnect/__init__.py
oshconnect/control.py
oshconnect/core_datamodels.py
oshconnect/datasource.py
oshconnect/datastore.py
oshconnect/osh_connect_datamodels.py
oshconnect/oshconnectapi.py
oshconnect/styling.py
oshconnect/timemanagement.py
oshconnect-0.2.4.post1.dist-info/licenses/LICENSE
oshconnect-0.2.4.post1.dist-info/METADATA
oshconnect-0.2.4.post1.dist-info/WHEEL
oshconnect-0.2.4.post1.dist-info/top_level.txt
oshconnect-0.2.4.post1.dist-info/RECORD
