Metadata-Version: 2.4
Name: oshconnect
Version: 0.2.4.post1
Summary: Library for interfacing with OSH, helping guide visualization efforts, and providing a place to store configurations.
Author-email: Ian Patterson <ian@botts-inc.com>
Requires-Python: <4.0,>=3.12
License-File: LICENSE
Requires-Dist: pydantic<3.0.0,>=2.7.4
Requires-Dist: shapely<3.0.0,>=2.0.4
Requires-Dist: websockets<13.0,>=12.0
Requires-Dist: consys4py<1.0.0,>=0.0.1b3
Requires-Dist: swecommondm<1.0.0,>=0.0.1a0
Dynamic: license-file
